main.py
hellojp/__init__.py
hellojp/main.py
hellojp-0.0.3.dist-info/LICENSE
hellojp-0.0.3.dist-info/METADATA
hellojp-0.0.3.dist-info/WHEEL
hellojp-0.0.3.dist-info/entry_points.txt
hellojp-0.0.3.dist-info/top_level.txt
hellojp-0.0.3.dist-info/RECORD
