Metadata-Version: 2.2
Name: hellojp
Version: 0.0.3
Summary: Example PyPI package
Author: JPBS
Author-email: jbuusao@jgmail.com
License-File: LICENSE
Requires-Dist: requests
Dynamic: author
Dynamic: author-email
Dynamic: description
Dynamic: description-content-type
Dynamic: requires-dist
Dynamic: summary
